{
  "id": "c0708dbd75954d9daa76458041e45ee0",
  "title": "Control Demo Audience",
  "description": "Control Demo Audience",
  "namespace": "calluna",
  "categories": "",
  "keyImages": [
    {
      "type": "ESRB",
      "url": "https://cdn1.epicgames.com/calluna/item/ESRB_Control-496x248-159f49def84c67c57a551259ef1216aa.jpg",
      "md5": "159f49def84c67c57a551259ef1216aa",
      "width": 496,
      "height": 248,
      "size": 11905,
      "uploadedDate": "2019-06-24T19:25:56.555Z"
    }
  ],
  "creationDate": "2019-06-24T19:26:13.923+00:00",
  "lastModifiedDate": "2023-08-18T09:53:30.542+00:00",
  "developer": "505 Games",
  "developerId": "o-cul2z53mrw3bxltv63v68rgd4b3w52",
  "applicationId": null
}