{
  "id": "2a8f3c0d466f47ca82a8553df6ed2f52",
  "title": "Vampire: The Masquerade \u2013 Bloodlines 2",
  "description": "Vampire: The Masquerade \u2013 Bloodlines 2",
  "namespace": "nemesia",
  "categories": "",
  "keyImages": [
    {
      "type": "DieselGameBox",
      "url": "https://cdn1.epicgames.com/item/nemesia/EGS_VampireTheMasqueradeBloodlines2_TheChineseRoom_S1_2560x1440-eed15ab6496fcba9770d4205aeb2aaf7",
      "md5": "eed15ab6496fcba9770d4205aeb2aaf7",
      "width": 2560,
      "height": 1440,
      "size": 532507,
      "uploadedDate": "2023-08-30T15:20:49.171Z"
    },
    {
      "type": "DieselGameBoxTall",
      "url": "https://cdn1.epicgames.com/item/nemesia/EGS_VampireTheMasqueradeBloodlines2_TheChineseRoom_S2_1200x1600-31c6dc03b2c02f7cf43b6df2972791bf",
      "md5": "31c6dc03b2c02f7cf43b6df2972791bf",
      "width": 1200,
      "height": 1600,
      "size": 339924,
      "uploadedDate": "2023-08-30T15:20:51.842Z"
    }
  ],
  "creationDate": "2019-03-13T12:11:22.827+00:00",
  "lastModifiedDate": "2024-04-02T16:37:45.022+00:00",
  "developer": "Paradox Interactive",
  "developerId": "o-tjvfg6rejs6h86qa7k9aa64rrgbxxb",
  "applicationId": ""
}