{
  "id": "c31030e542f246e299305209352aac2b",
  "title": "PetuniaGeneralAudience",
  "description": "PetuniaGeneralAudience",
  "namespace": "petunia",
  "categories": "",
  "keyImages": [
    {
      "type": "ESRB",
      "url": "https://cdn1.epicgames.com/petunia/item/ESRB_MetroLastLight-842x404-699f2f88320405267d8acb6bb327b32b.png",
      "md5": "699f2f88320405267d8acb6bb327b32b",
      "width": 842,
      "height": 404,
      "size": 59015,
      "uploadedDate": "2019-04-30T21:40:02.997Z"
    }
  ],
  "creationDate": "2019-01-29T15:18:57.742+00:00",
  "lastModifiedDate": "2022-09-20T15:00:41.488+00:00",
  "developer": "Plaion",
  "developerId": "o-jskfz28ywm2l56px6h9rlxplaysrtl",
  "applicationId": ""
}